MANIFEST.in
README.md
VERSION
requirements.txt
setup.py
docs/source/conf.py
examples/basic_create_jws.py
examples/basic_decode_jwt.py
examples/keyloader_jwks.py
unimatrix.ext.jose.egg-info/PKG-INFO
unimatrix.ext.jose.egg-info/SOURCES.txt
unimatrix.ext.jose.egg-info/dependency_links.txt
unimatrix.ext.jose.egg-info/entry_points.txt
unimatrix.ext.jose.egg-info/requires.txt
unimatrix.ext.jose.egg-info/top_level.txt
unimatrix/ext/jose/__init__.py
unimatrix/ext/jose/__ioc__.py
unimatrix/ext/jose/algorithms.py
unimatrix/ext/jose/const.py
unimatrix/ext/jose/decoder.py
unimatrix/ext/jose/exceptions.py
unimatrix/ext/jose/header.py
unimatrix/ext/jose/jwk.py
unimatrix/ext/jose/jws.py
unimatrix/ext/jose/jwt.py
unimatrix/ext/jose/oauth2metadataloader.py
unimatrix/ext/jose/package.json
unimatrix/ext/jose/resolver.py
unimatrix/ext/jose/signature.py
unimatrix/ext/jose/utils.py
unimatrix/ext/jose/tests/__init__.py
unimatrix/ext/jose/tests/const.py
unimatrix/ext/jose/tests/key.rsa
unimatrix/ext/jose/tests/pub.rsa
unimatrix/ext/jose/tests/signer.py
unimatrix/ext/jose/tests/test_integration_compat_jwt.py
unimatrix/ext/jose/tests/test_integration_jws.py
unimatrix/ext/jose/tests/test_integration_jwt.py
unimatrix/ext/jose/tests/test_integration_key_id.py
unimatrix/ext/jose/tests/test_integration_payload.py
unimatrix/ext/jose/tests/test_unit_jose_header.py
unimatrix/ext/jose/tests/test_unit_jwt.py
unimatrix/ext/jose/tests/test_unit_jwt_aud.py
unimatrix/ext/jose/tests/test_unit_jwt_exp.py
unimatrix/ext/jose/tests/test_unit_jwt_iss.py
unimatrix/ext/jose/tests/test_unit_jwt_scopes.py
unimatrix/ext/jose/tests/test_unit_setup_ioc.py